{
  "updated_at": "2026-07-10T01:45:26Z",
  "current": {
    "xauusd": {
      "symbol": "GC=F",
      "price": 4129.7998,
      "change": 0.7998,
      "change_pct": 0.019
    },
    "xagusd": {
      "symbol": "SI=F",
      "price": 60.435,
      "change": 0.0,
      "change_pct": 0.0
    },
    "platinum": {
      "symbol": "PL=F",
      "price": 1629.7,
      "change": -0.1001,
      "change_pct": -0.006
    },
    "dxy": {
      "symbol": "DX-Y.NYB",
      "price": 100.764,
      "change": -0.002,
      "change_pct": -0.002
    },
    "usdkrw": {
      "symbol": "KRW=X",
      "price": 1512.05,
      "change": -0.23,
      "change_pct": -0.015
    },
    "usdjpy": {
      "symbol": "JPY=X",
      "price": 161.834,
      "change": -0.016,
      "change_pct": -0.01
    },
    "eurusd": {
      "symbol": "EURUSD=X",
      "price": 1.1447,
      "change": -0.0001,
      "change_pct": -0.009
    },
    "tnx": {
      "symbol": "^TNX",
      "price": 4.539,
      "change": 0.0,
      "change_pct": 0.0
    },
    "irx": {
      "symbol": "^IRX",
      "price": 3.682,
      "change": 0.0,
      "change_pct": 0.0
    },
    "wti": {
      "symbol": "CL=F",
      "price": 72.08,
      "change": 0.02,
      "change_pct": 0.028
    },
    "sp500": {
      "symbol": "^GSPC",
      "price": 7542.2798,
      "change": 1.0596,
      "change_pct": 0.014
    },
    "nasdaq": {
      "symbol": "^IXIC",
      "price": 26203.4805,
      "change": -2.3105,
      "change_pct": -0.009
    },
    "vix": {
      "symbol": "^VIX",
      "price": 15.84,
      "change": -0.01,
      "change_pct": -0.063
    },
    "copper": {
      "symbol": "HG=F",
      "price": 6.2695,
      "change": -0.0005,
      "change_pct": -0.008
    }
  }
}