{
  "updated_at": "2026-07-21T13:30:42Z",
  "current": {
    "xauusd": {
      "symbol": "GC=F",
      "price": 4060.0,
      "change": 0.3999,
      "change_pct": 0.01
    },
    "xagusd": {
      "symbol": "SI=F",
      "price": 58.97,
      "change": -0.05,
      "change_pct": -0.085
    },
    "platinum": {
      "symbol": "PL=F",
      "price": 1622.5,
      "change": -0.4,
      "change_pct": -0.025
    },
    "dxy": {
      "symbol": "DX-Y.NYB",
      "price": 101.055,
      "change": 0.004,
      "change_pct": 0.004
    },
    "usdkrw": {
      "symbol": "KRW=X",
      "price": 1479.41,
      "change": 0.0701,
      "change_pct": 0.005
    },
    "usdjpy": {
      "symbol": "JPY=X",
      "price": 162.798,
      "change": 0.009,
      "change_pct": 0.006
    },
    "eurusd": {
      "symbol": "EURUSD=X",
      "price": 1.1414,
      "change": 0.0001,
      "change_pct": 0.009
    },
    "tnx": {
      "symbol": "^TNX",
      "price": 4.608,
      "change": 0.002,
      "change_pct": 0.043
    },
    "irx": {
      "symbol": "^IRX",
      "price": 3.72,
      "change": 0.0,
      "change_pct": 0.0
    },
    "wti": {
      "symbol": "CL=F",
      "price": 84.29,
      "change": 0.06,
      "change_pct": 0.071
    },
    "sp500": {
      "symbol": "^GSPC",
      "price": 7486.8599,
      "change": 42.1299,
      "change_pct": 0.566
    },
    "nasdaq": {
      "symbol": "^IXIC",
      "price": 25749.6855,
      "change": 239.4199,
      "change_pct": 0.939
    },
    "vix": {
      "symbol": "^VIX",
      "price": 17.82,
      "change": 0.0,
      "change_pct": 0.0
    },
    "copper": {
      "symbol": "HG=F",
      "price": 6.5135,
      "change": -0.0035,
      "change_pct": -0.054
    }
  }
}