{
  "updated_at": "2026-07-09T17:25:24Z",
  "current": {
    "xauusd": {
      "symbol": "GC=F",
      "price": 4135.8999,
      "change": -1.3003,
      "change_pct": -0.031
    },
    "xagusd": {
      "symbol": "SI=F",
      "price": 60.65,
      "change": -0.045,
      "change_pct": -0.074
    },
    "platinum": {
      "symbol": "PL=F",
      "price": 1626.2,
      "change": -0.3,
      "change_pct": -0.018
    },
    "dxy": {
      "symbol": "DX-Y.NYB",
      "price": 100.89,
      "change": 0.0,
      "change_pct": 0.0
    },
    "usdkrw": {
      "symbol": "KRW=X",
      "price": 1508.9301,
      "change": 0.2001,
      "change_pct": 0.013
    },
    "usdjpy": {
      "symbol": "JPY=X",
      "price": 162.282,
      "change": -0.002,
      "change_pct": -0.001
    },
    "eurusd": {
      "symbol": "EURUSD=X",
      "price": 1.1443,
      "change": 0.0,
      "change_pct": 0.0
    },
    "tnx": {
      "symbol": "^TNX",
      "price": 4.539,
      "change": 0.002,
      "change_pct": 0.044
    },
    "irx": {
      "symbol": "^IRX",
      "price": 3.688,
      "change": 0.0,
      "change_pct": 0.0
    },
    "wti": {
      "symbol": "CL=F",
      "price": 72.07,
      "change": 0.03,
      "change_pct": 0.042
    },
    "sp500": {
      "symbol": "^GSPC",
      "price": 7542.46,
      "change": 0.6499,
      "change_pct": 0.009
    },
    "nasdaq": {
      "symbol": "^IXIC",
      "price": 26172.0703,
      "change": 0.8418,
      "change_pct": 0.003
    },
    "vix": {
      "symbol": "^VIX",
      "price": 15.96,
      "change": 0.0,
      "change_pct": 0.0
    },
    "copper": {
      "symbol": "HG=F",
      "price": 6.255,
      "change": -0.001,
      "change_pct": -0.016
    }
  }
}