{
  "updated_at": "2026-07-02T14:40:34Z",
  "current": {
    "xauusd": {
      "symbol": "GC=F",
      "price": 4131.7002,
      "change": 2.6001,
      "change_pct": 0.063
    },
    "xagusd": {
      "symbol": "SI=F",
      "price": 61.715,
      "change": 0.045,
      "change_pct": 0.073
    },
    "platinum": {
      "symbol": "PL=F",
      "price": 1628.0,
      "change": 1.7,
      "change_pct": 0.105
    },
    "dxy": {
      "symbol": "DX-Y.NYB",
      "price": 100.778,
      "change": 0.0,
      "change_pct": 0.0
    },
    "usdkrw": {
      "symbol": "KRW=X",
      "price": 1543.59,
      "change": 0.4099,
      "change_pct": 0.027
    },
    "usdjpy": {
      "symbol": "JPY=X",
      "price": 161.05,
      "change": 0.01,
      "change_pct": 0.006
    },
    "eurusd": {
      "symbol": "EURUSD=X",
      "price": 1.1442,
      "change": -0.0001,
      "change_pct": -0.009
    },
    "tnx": {
      "symbol": "^TNX",
      "price": 4.479,
      "change": 0.0,
      "change_pct": 0.0
    },
    "irx": {
      "symbol": "^IRX",
      "price": 3.66,
      "change": -0.003,
      "change_pct": -0.082
    },
    "wti": {
      "symbol": "CL=F",
      "price": 67.67,
      "change": 0.06,
      "change_pct": 0.089
    },
    "sp500": {
      "symbol": "^GSPC",
      "price": 7513.1699,
      "change": 1.2798,
      "change_pct": 0.017
    },
    "nasdaq": {
      "symbol": "^IXIC",
      "price": 26054.5527,
      "change": 5.2598,
      "change_pct": 0.02
    },
    "vix": {
      "symbol": "^VIX",
      "price": 16.01,
      "change": 0.07,
      "change_pct": 0.439
    },
    "copper": {
      "symbol": "HG=F",
      "price": 6.189,
      "change": 0.007,
      "change_pct": 0.113
    }
  }
}