{
  "updated_at": "2026-06-25T15:30:35Z",
  "current": {
    "xauusd": {
      "symbol": "GC=F",
      "price": 4029.1001,
      "change": -1.3999,
      "change_pct": -0.035
    },
    "xagusd": {
      "symbol": "SI=F",
      "price": 57.92,
      "change": 0.01,
      "change_pct": 0.017
    },
    "gold": {
      "symbol": "GC=F",
      "price": 4029.1001,
      "change": -1.3999,
      "change_pct": -0.035
    },
    "silver": {
      "symbol": "SI=F",
      "price": 57.92,
      "change": 0.01,
      "change_pct": 0.017
    },
    "platinum": {
      "symbol": "PL=F",
      "price": 1611.2,
      "change": 0.5,
      "change_pct": 0.031
    },
    "dxy": {
      "symbol": "DX-Y.NYB",
      "price": 101.377,
      "change": 0.003,
      "change_pct": 0.003
    },
    "usdkrw": {
      "symbol": "KRW=X",
      "price": 1540.58,
      "change": 0.0399,
      "change_pct": 0.003
    },
    "usdjpy": {
      "symbol": "JPY=X",
      "price": 161.648,
      "change": -0.002,
      "change_pct": -0.001
    },
    "eurusd": {
      "symbol": "EURUSD=X",
      "price": 1.139,
      "change": -0.0001,
      "change_pct": -0.009
    },
    "tnx": {
      "symbol": "^TNX",
      "price": 4.388,
      "change": 0.004,
      "change_pct": 0.091
    },
    "irx": {
      "symbol": "^IRX",
      "price": 3.682,
      "change": 0.0,
      "change_pct": 0.0
    },
    "wti": {
      "symbol": "CL=F",
      "price": 71.52,
      "change": -0.09,
      "change_pct": -0.126
    },
    "sp500": {
      "symbol": "^GSPC",
      "price": 7370.5498,
      "change": 0.8198,
      "change_pct": 0.011
    },
    "nasdaq": {
      "symbol": "^IXIC",
      "price": 25349.043,
      "change": 12.209,
      "change_pct": 0.048
    },
    "vix": {
      "symbol": "^VIX",
      "price": 19.54,
      "change": 0.2,
      "change_pct": 1.034
    },
    "copper": {
      "symbol": "HG=F",
      "price": 6.11,
      "change": -0.002,
      "change_pct": -0.033
    }
  }
}