{
  "updated_at": "2026-07-16T17:05:33Z",
  "current": {
    "xauusd": {
      "symbol": "GC=F",
      "price": 4001.3,
      "change": 2.1001,
      "change_pct": 0.053
    },
    "xagusd": {
      "symbol": "SI=F",
      "price": 56.43,
      "change": 0.045,
      "change_pct": 0.08
    },
    "platinum": {
      "symbol": "PL=F",
      "price": 1649.8,
      "change": 0.5,
      "change_pct": 0.03
    },
    "dxy": {
      "symbol": "DX-Y.NYB",
      "price": 100.782,
      "change": -0.009,
      "change_pct": -0.009
    },
    "usdkrw": {
      "symbol": "KRW=X",
      "price": 1480.37,
      "change": 0.13,
      "change_pct": 0.009
    },
    "usdjpy": {
      "symbol": "JPY=X",
      "price": 162.491,
      "change": 0.001,
      "change_pct": 0.001
    },
    "eurusd": {
      "symbol": "EURUSD=X",
      "price": 1.1436,
      "change": 0.0001,
      "change_pct": 0.009
    },
    "tnx": {
      "symbol": "^TNX",
      "price": 4.577,
      "change": -0.003,
      "change_pct": -0.066
    },
    "irx": {
      "symbol": "^IRX",
      "price": 3.695,
      "change": 0.0,
      "change_pct": 0.0
    },
    "wti": {
      "symbol": "CL=F",
      "price": 78.31,
      "change": -0.15,
      "change_pct": -0.191
    },
    "sp500": {
      "symbol": "^GSPC",
      "price": 7549.1001,
      "change": -2.8701,
      "change_pct": -0.038
    },
    "nasdaq": {
      "symbol": "^IXIC",
      "price": 26014.5234,
      "change": -16.9141,
      "change_pct": -0.065
    },
    "vix": {
      "symbol": "^VIX",
      "price": 16.28,
      "change": -0.04,
      "change_pct": -0.245
    },
    "copper": {
      "symbol": "HG=F",
      "price": 6.341,
      "change": 0.002,
      "change_pct": 0.032
    }
  }
}