{
  "updated_at": "2026-06-29T15:40:38Z",
  "current": {
    "xauusd": {
      "symbol": "GC=F",
      "price": 4039.8,
      "change": 1.4001,
      "change_pct": 0.035
    },
    "xagusd": {
      "symbol": "SI=F",
      "price": 58.395,
      "change": 0.025,
      "change_pct": 0.043
    },
    "platinum": {
      "symbol": "PL=F",
      "price": 1592.5,
      "change": 1.0,
      "change_pct": 0.063
    },
    "dxy": {
      "symbol": "DX-Y.NYB",
      "price": 101.14,
      "change": -0.004,
      "change_pct": -0.004
    },
    "usdkrw": {
      "symbol": "KRW=X",
      "price": 1542.99,
      "change": 1.3099,
      "change_pct": 0.085
    },
    "usdjpy": {
      "symbol": "JPY=X",
      "price": 161.941,
      "change": 0.002,
      "change_pct": 0.001
    },
    "eurusd": {
      "symbol": "EURUSD=X",
      "price": 1.1425,
      "change": 0.0,
      "change_pct": 0.0
    },
    "tnx": {
      "symbol": "^TNX",
      "price": 4.38,
      "change": 0.0,
      "change_pct": 0.0
    },
    "irx": {
      "symbol": "^IRX",
      "price": 3.66,
      "change": 0.0,
      "change_pct": 0.0
    },
    "wti": {
      "symbol": "CL=F",
      "price": 70.51,
      "change": 0.03,
      "change_pct": 0.043
    },
    "sp500": {
      "symbol": "^GSPC",
      "price": 7407.1299,
      "change": -1.4199,
      "change_pct": -0.019
    },
    "nasdaq": {
      "symbol": "^IXIC",
      "price": 25626.6113,
      "change": -7.6875,
      "change_pct": -0.03
    },
    "vix": {
      "symbol": "^VIX",
      "price": 18.35,
      "change": -0.01,
      "change_pct": -0.054
    },
    "copper": {
      "symbol": "HG=F",
      "price": 6.15,
      "change": -0.001,
      "change_pct": -0.016
    }
  }
}