{
  "updated_at": "2026-07-01T01:40:27Z",
  "current": {
    "xauusd": {
      "symbol": "GC=F",
      "price": 3999.8,
      "change": 1.2,
      "change_pct": 0.03
    },
    "xagusd": {
      "symbol": "SI=F",
      "price": 58.46,
      "change": 0.04,
      "change_pct": 0.068
    },
    "platinum": {
      "symbol": "PL=F",
      "price": 1554.8,
      "change": 0.7001,
      "change_pct": 0.045
    },
    "dxy": {
      "symbol": "DX-Y.NYB",
      "price": 101.297,
      "change": 0.0,
      "change_pct": 0.0
    },
    "usdkrw": {
      "symbol": "KRW=X",
      "price": 1558.6899,
      "change": 0.12,
      "change_pct": 0.008
    },
    "usdjpy": {
      "symbol": "JPY=X",
      "price": 162.641,
      "change": 0.012,
      "change_pct": 0.007
    },
    "eurusd": {
      "symbol": "EURUSD=X",
      "price": 1.1409,
      "change": 0.0,
      "change_pct": 0.0
    },
    "tnx": {
      "symbol": "^TNX",
      "price": 4.418,
      "change": 0.002,
      "change_pct": 0.045
    },
    "irx": {
      "symbol": "^IRX",
      "price": 3.732,
      "change": 0.0,
      "change_pct": 0.0
    },
    "wti": {
      "symbol": "CL=F",
      "price": 69.92,
      "change": -0.01,
      "change_pct": -0.014
    },
    "sp500": {
      "symbol": "^GSPC",
      "price": 7496.3101,
      "change": -5.71,
      "change_pct": -0.076
    },
    "nasdaq": {
      "symbol": "^IXIC",
      "price": 26203.1816,
      "change": -26.0254,
      "change_pct": -0.099
    },
    "vix": {
      "symbol": "^VIX",
      "price": 16.45,
      "change": -0.02,
      "change_pct": -0.121
    },
    "copper": {
      "symbol": "HG=F",
      "price": 6.195,
      "change": 0.004,
      "change_pct": 0.065
    }
  }
}